showmethetypes/__init__.py
showmethetypes/core.py
showmethetypes/handlers.py
showmethetypes/registry.py
showmethetypes-0.1.dist-info/LICENSE
showmethetypes-0.1.dist-info/METADATA
showmethetypes-0.1.dist-info/WHEEL
showmethetypes-0.1.dist-info/top_level.txt
showmethetypes-0.1.dist-info/RECORD
