Metadata-Version: 2.1
Name: showmethetypes
Version: 0.1
Summary: A one-function package designed to do one thing.. show you the types!
Author-email: Jack Strand <JackOfTheStrand@gmail.com>
Project-URL: Homepage, https://github.com/InfiniteSwerve/showmethetypes
Classifier: Programming Language :: Python :: 3
Classifier: License :: OSI Approved :: GNU General Public License (GPL)
Classifier: Operating System :: OS Independent
Requires-Python: >=3.8
License-File: LICENSE
